apiclient/__init__.py
apiclient/apiclient.py
apiclient_gonzalo123-1.0.2.dist-info/METADATA
apiclient_gonzalo123-1.0.2.dist-info/WHEEL
apiclient_gonzalo123-1.0.2.dist-info/top_level.txt
apiclient_gonzalo123-1.0.2.dist-info/RECORD
