Metadata-Version: 2.1
Name: apiclient-gonzalo123
Version: 1.0.2
Summary: apiclient
Home-page: https://github.com/gonzalo123/apiclient
Author: Gonzalo Ayuso
Author-email: gonzalo123@gmail.com
License: MIT
Keywords: apiclient
Classifier: Programming Language :: Python :: 3
Classifier: License :: OSI Approved :: MIT License
Classifier: Operating System :: OS Independent
Requires-Python: >=3.5
Requires-Dist: requests (>=2.3.0)
